[
  { "country": "AD", "length": 24, "regex": "^AD\\d{10}[A-Z0-9]{12}$" },
  { "country": "AE", "length": 23, "regex": "^AE\\d{21}$" },
  { "country": "AL", "length": 28, "regex": "^AL\\d{10}[A-Z0-9]{16}$" },
  { "country": "AT", "length": 20, "regex": "^AT\\d{18}$" },
  { "country": "AZ", "length": 28, "regex": "^AZ\\d{2}[A-Z]{4}[A-Z0-9]{20}$" },
  { "country": "BA", "length": 20, "regex": "^BA\\d{18}$" },
  { "country": "BE", "length": 16, "regex": "^BE\\d{14}$" },
  { "country": "BG", "length": 22, "regex": "^BG\\d{2}[A-Z]{4}\\d{6}[A-Z0-9]{8}$" },
  { "country": "BH", "length": 22, "regex": "^BH\\d{2}[A-Z]{4}[A-Z0-9]{14}$" },
  { "country": "BI", "length": 27, "regex": "^BI\\d{25}$" },
  { "country": "BR", "length": 29, "regex": "^BR\\d{25}[A-Z][A-Z0-9]$" },
  { "country": "BY", "length": 28, "regex": "^BY\\d{2}[A-Z0-9]{4}\\d{4}[A-Z0-9]{16}$" },
  { "country": "CH", "length": 21, "regex": "^CH\\d{7}[A-Z0-9]{12}$" },
  { "country": "CR", "length": 22, "regex": "^CR\\d{2}0\\d{17}$" },
  { "country": "CY", "length": 28, "regex": "^CY\\d{10}[A-Z0-9]{16}$" },
  { "country": "CZ", "length": 24, "regex": "^CZ\\d{22}$" },
  { "country": "DE", "length": 22, "regex": "^DE\\d{20}$" },
  { "country": "DK", "length": 18, "regex": "^DK\\d{16}$" },
  { "country": "DO", "length": 28, "regex": "^DO\\d{2}[A-Z0-9]{4}\\d{20}$" },
  { "country": "EE", "length": 20, "regex": "^EE\\d{18}$" },
  { "country": "EG", "length": 29, "regex": "^EG\\d{27}$" },
  { "country": "ES", "length": 24, "regex": "^ES\\d{22}$" },
  { "country": "FI", "length": 18, "regex": "^FI\\d{16}$" },
  { "country": "FO", "length": 18, "regex": "^FO\\d{16}$" },
  { "country": "FR", "length": 27, "regex": "^FR\\d{12}[A-Z0-9]{11}\\d{2}$" },
  { "country": "GB", "length": 22, "regex": "^GB\\d{2}[A-Z]{4}\\d{14}$" },
  { "country": "GE", "length": 22, "regex": "^GE\\d{2}[A-Z]{2}\\d{16}$" },
  { "country": "GI", "length": 23, "regex": "^GI\\d{2}[A-Z]{4}[A-Z0-9]{15}$" },
  { "country": "GL", "length": 18, "regex": "^GL\\d{16}$" },
  { "country": "GR", "length": 27, "regex": "^GR\\d{9}[A-Z0-9]{16}$" },
  { "country": "GT", "length": 28, "regex": "^GT\\d{2}[A-Z0-9]{24}$" },
  { "country": "HR", "length": 21, "regex": "^HR\\d{19}$" },
  { "country": "HU", "length": 28, "regex": "^HU\\d{26}$" },
  { "country": "IE", "length": 22, "regex": "^IE\\d{2}[A-Z]{4}\\d{14}$" },
  { "country": "IL", "length": 23, "regex": "^IL\\d{25}$" },
  { "country": "IQ", "length": 23, "regex": "^IQ\\d{2}[A-Z]{4}\\d{15}$" },
  { "country": "IS", "length": 26, "regex": "^IS\\d{24}$" },
  { "country": "IT", "length": 27, "regex": "^IT\\d{2}[A-Z]\\d{10}[A-Z0-9]{12}$" },
  { "country": "JO", "length": 30, "regex": "^JO\\d{2}[A-Z]{4}\\d{4}[A-Z0-9]{18}$" },
  { "country": "KW", "length": 30, "regex": "^KW\\d{2}[A-Z]{4}[A-Z0-9]{22}$" },
  { "country": "KZ", "length": 20, "regex": "^KZ\\d{5}[A-Z0-9]{13}$" },
  { "country": "LB", "length": 28, "regex": "^LB\\d{6}[A-Z0-9]{20}$" },
  { "country": "LC", "length": 32, "regex": "^LC\\d{2}[A-Z]{4}[A-Z0-9]{24}$" },
  { "country": "LI", "length": 21, "regex": "^LI\\d{7}[A-Z0-9]{12}$" },
  { "country": "LT", "length": 20, "regex": "^LT\\d{18}$" },
  { "country": "LU", "length": 20, "regex": "^LU\\d{5}[A-Z0-9]{13}$" },
  { "country": "LV", "length": 21, "regex": "^LV\\d{2}[A-Z]{4}[A-Z0-9]{13}$" },
  { "country": "LY", "length": 25, "regex": "^LY\\d{23}$" },
  { "country": "MC", "length": 27, "regex": "^MC\\d{12}[A-Z0-9]{11}\\d{2}$" },
  { "country": "MD", "length": 24, "regex": "^MD\\d{2}[A-Z0-9]{20}$" },
  { "country": "ME", "length": 22, "regex": "^ME\\d{20}$" },
  { "country": "MK", "length": 19, "regex": "^MK\\d{5}[A-Z0-9]{10}\\d{2}$" },
  { "country": "MR", "length": 27, "regex": "^MR\\d{25}$" },
  { "country": "MT", "length": 31, "regex": "^MT\\d{2}[A-Z]{4}\\d{5}[A-Z0-9]{18}$" },
  { "country": "MU", "length": 30, "regex": "^MU\\d{2}[A-Z]{4}\\d{19}[A-Z]{3}$" },
  { "country": "NL", "length": 18, "regex": "^NL\\d{2}[A-Z]{4}\\d{10}$" },
  { "country": "NO", "length": 15, "regex": "^NO\\d{13}$" },
  { "country": "PK", "length": 24, "regex": "^PK\\d{2}[A-Z]{4}[A-Z0-9]{16}$" },
  { "country": "PL", "length": 28, "regex": "^PL\\d{26}$" },
  { "country": "PS", "length": 29, "regex": "^PS\\d{2}[A-Z]{4}[A-Z0-9]{21}$" },
  { "country": "PT", "length": 25, "regex": "^PT\\d{23}$" },
  { "country": "QA", "length": 29, "regex": "^QA\\d{2}[A-Z]{4}[A-Z0-9]{21}$" },
  { "country": "RO", "length": 24, "regex": "^RO\\d{2}[A-Z]{4}[A-Z0-9]{16}$" },
  { "country": "RS", "length": 22, "regex": "^RS\\d{20}$" },
  { "country": "SA", "length": 24, "regex": "^SA\\d{4}[A-Z0-9]{18}$" },
  { "country": "SC", "length": 31, "regex": "^SC\\d{2}[A-Z]{4}\\d{20}[A-Z]{3}$" },
  { "country": "SE", "length": 24, "regex": "^SE\\d{22}$" },
  { "country": "SI", "length": 19, "regex": "^SI\\d{17}$" },
  { "country": "SK", "length": 24, "regex": "^SK\\d{22}$" },
  { "country": "SM", "length": 27, "regex": "^SM\\d{2}[A-Z]\\d{10}[A-Z0-9]{12}$" },
  { "country": "ST", "length": 25, "regex": "^ST\\d{23}$" },
  { "country": "SV", "length": 28, "regex": "^SV\\d{2}[A-Z]{4}\\d{20}$" },
  { "country": "TL", "length": 23, "regex": "^TL\\d{21}$" },
  { "country": "TN", "length": 24, "regex": "^TN\\d{22}$" },
  { "country": "TR", "length": 26, "regex": "^TR\\d{7}[A-Z0-9]{17}$" },
  { "country": "UA", "length": 29, "regex": "^UA\\d{8}[A-Z0-9]{19}$" },
  { "country": "VA", "length": 22, "regex": "^VA\\d{20}$" },
  { "country": "VG", "length": 24, "regex": "^VG\\d{2}[A-Z]{4}\\d{16}$" },
  { "country": "XK", "length": 20, "regex": "^XK\\d{18}$" }
]
